dash_leaflet/AttributionControl.py
dash_leaflet/BaseLayer.py
dash_leaflet/Circle.py
dash_leaflet/CircleMarker.py
dash_leaflet/Colorbar.py
dash_leaflet/DivMarker.py
dash_leaflet/EasyButton.py
dash_leaflet/EditControl.py
dash_leaflet/FeatureGroup.py
dash_leaflet/FullScreenControl.py
dash_leaflet/GeoJSON.py
dash_leaflet/GestureHandling.py
dash_leaflet/ImageOverlay.py
dash_leaflet/LayerGroup.py
dash_leaflet/LayersControl.py
dash_leaflet/LocateControl.py
dash_leaflet/MapContainer.py
dash_leaflet/Marker.py
dash_leaflet/MeasureControl.py
dash_leaflet/Overlay.py
dash_leaflet/Pane.py
dash_leaflet/Polygon.py
dash_leaflet/Polyline.py
dash_leaflet/PolylineDecorator.py
dash_leaflet/Popup.py
dash_leaflet/Rectangle.py
dash_leaflet/SVGOverlay.py
dash_leaflet/ScaleControl.py
dash_leaflet/TileLayer.py
dash_leaflet/Tooltip.py
dash_leaflet/VideoOverlay.py
dash_leaflet/WMSTileLayer.py
dash_leaflet/ZoomControl.py
dash_leaflet/__init__.py
dash_leaflet/_imports_.py
dash_leaflet/async-EditControl.ts.js
dash_leaflet/async-GeoJSON.js
dash_leaflet/async-LocateControl.js
dash_leaflet/async-MeasureControl.js
dash_leaflet/async-flatgeobuf.js
dash_leaflet/async-geobuf.js
dash_leaflet/dash_leaflet.js
dash_leaflet/express.py
dash_leaflet/metadata.json
dash_leaflet/package-info.json
dash_leaflet/proptypes.js
dash_leaflet-1.1.2.dist-info/licenses/LICENSE
dash_leaflet-1.1.2.dist-info/METADATA
dash_leaflet-1.1.2.dist-info/WHEEL
dash_leaflet-1.1.2.dist-info/top_level.txt
dash_leaflet-1.1.2.dist-info/RECORD
