Metadata-Version: 2.4
Name: dash-leaflet
Version: 1.1.2
Summary: Dash Leaflet is a light wrapper around React-Leaflet. The syntax is similar to other Dash components, with naming conventions following the React-Leaflet API.
Author: Emil Haldrup Eriksen <emil.h.eriksen@gmail.com>
Author-email: emher <emil.h.eriksen@gmail.com>
License-Expression: MIT
Project-URL: homepage, https://dash-leaflet.com
Project-URL: repository, https://github.com/emilhe/dash-leaflet
Requires-Python: >=3.12
License-File: LICENSE
Requires-Dist: dash>=3.0.0
Requires-Dist: dash-extensions>=2.0.0
Requires-Dist: dash_svg
Requires-Dist: protobuf>=6.30.2
Requires-Dist: geobuf>=2.0.0
Requires-Dist: pyyaml
Requires-Dist: colorcet
Dynamic: author
Dynamic: license-file
